owm2json/__init__.py
owm2json/owm2json.py
owm2json/version.py
owm2json-0.1.89.dist-info/LICENSE
owm2json-0.1.89.dist-info/METADATA
owm2json-0.1.89.dist-info/WHEEL
owm2json-0.1.89.dist-info/top_level.txt
owm2json-0.1.89.dist-info/RECORD
