Metadata-Version: 2.1
Name: owm2json
Version: 0.1.89
Summary: Python module for getting several of OpenWeatherMap API at once
Home-page: https://github.com/viktak/owm2json
Author: @viktak
Author-email: owm2json@viktak.com
License: UNKNOWN
Project-URL: Bug Tracker, https://github.com/viktak/owm2json/issues
Platform: UNKNOWN
Classifier: Programming Language :: Python :: 3
Classifier: License :: OSI Approved :: GNU General Public License v3 (GPLv3)
Classifier: Operating System :: OS Independent
Requires-Python: >=3.7
